d_oss/__init__.py
d_oss/__main__.py
d_oss-0.3.1.dist-info/METADATA
d_oss-0.3.1.dist-info/WHEEL
d_oss-0.3.1.dist-info/entry_points.txt
d_oss-0.3.1.dist-info/RECORD
