Metadata-Version: 2.4
Name: d-oss
Version: 0.3.1
Summary: 基于阿里云对象存储的命令行应用
Author-email: wangmengdi <790990241@qq.com>
Requires-Python: >=3.10
Requires-Dist: jsonargparse[signatures]>=4.38.0
Requires-Dist: oss2>=2.19.1
Requires-Dist: rich>=13.9.4
Requires-Dist: srsly>=2.5.1
